compare_packages/__init__.py
compare_packages/cli.py
compare_packages/compare_packages.py
compare_packages-0.1.dist-info/LICENSE
compare_packages-0.1.dist-info/METADATA
compare_packages-0.1.dist-info/WHEEL
compare_packages-0.1.dist-info/entry_points.txt
compare_packages-0.1.dist-info/top_level.txt
compare_packages-0.1.dist-info/RECORD
