Metadata-Version: 2.1
Name: compare-packages
Version: 0.1
Summary: library for comparing two branches
Home-page: https://github.com/aksalena/compare_packages
Author: Alena Guseva
Author-email: axenova.ale@mail.ru
License: UNKNOWN
Platform: UNKNOWN
Classifier: Programming Language :: Python :: 3
Classifier: License :: OSI Approved :: MIT License
License-File: LICENSE
Requires-Dist: requests
